math_calculator/__init__.py
math_calculator/calculator.py
math_calculator/tests/__init__.py
math_calculator/tests/test_calculator.py
math_calculator-1.0.1.dist-info/LICENSE
math_calculator-1.0.1.dist-info/METADATA
math_calculator-1.0.1.dist-info/WHEEL
math_calculator-1.0.1.dist-info/top_level.txt
math_calculator-1.0.1.dist-info/RECORD
